termprint/__about__.py
termprint/__init__.py
termprint/print.py
termprint/print_examples.py
termprint-0.0.5.dist-info/METADATA
termprint-0.0.5.dist-info/WHEEL
termprint-0.0.5.dist-info/entry_points.txt
termprint-0.0.5.dist-info/licenses/LICENSE.txt
termprint-0.0.5.dist-info/RECORD
