Metadata-Version: 2.4
Name: termprint
Version: 0.0.5
Project-URL: Documentation, https://github.com/thhapke/termprint#readme
Project-URL: Issues, https://github.com/thhapke/pytermprint/issues
Project-URL: Source, https://github.com/thhapke/pytermprint
Author-email: Thorsten Hapke <thorsten.hapke@sap.com>
License-Expression: MIT
License-File: LICENSE.txt
Classifier: Development Status :: 4 - Beta
Classifier: Programming Language :: Python
Classifier: Programming Language :: Python :: 3.10
Classifier: Programming Language :: Python :: 3.11
Classifier: Programming Language :: Python :: 3.12
Classifier: Programming Language :: Python :: Implementation :: CPython
Classifier: Programming Language :: Python :: Implementation :: PyPy
Requires-Python: >=3.10
